MANIFEST.in
README.rst
setup.cfg
setup.py
docs/source/conf.py
docs/source/index.rst
procfs/__init__.py
procfs/core.py
procfs/exceptions.py
procfs/utils.py
procfs.egg-info/PKG-INFO
procfs.egg-info/SOURCES.txt
procfs.egg-info/dependency_links.txt
procfs.egg-info/top_level.txt
procfs/proc/__init__.py
procfs/proc/fs/__init__.py
procfs/proc/fs/nfsd.py
procfs/processes/__init__.py
procfs/processes/net/__init__.py
procfs/processes/net/rpc.py