Metadata-Version: 1.0
Name: procfs
Version: 0.1.2
Summary: Python API for the Linux /proc virtual filesystem
Home-page: https://github.com/pmuller/procfs
Author: Philippe Muller
Author-email: philippe.muller@gmail.com
License: BSD
Keywords: linux proc procfs system kernel
Platform: Linux
Classifier: Development Status :: 3 - Alpha
Classifier: Intended Audience :: System Administrators
Classifier: Intended Audience :: Developers
Classifier: License :: OSI Approved :: BSD License
Classifier: Operating System :: POSIX :: Linux
Classifier: Topic :: System :: Operating System Kernels :: Linux
Classifier: Topic :: Software Development :: Libraries :: Python Modules
